finra_api_queries/__init__.py
finra_api_queries/finra_api_queries.py
finra_api_queries-1.2.1.dist-info/LICENSE
finra_api_queries-1.2.1.dist-info/WHEEL
finra_api_queries-1.2.1.dist-info/METADATA
finra_api_queries-1.2.1.dist-info/RECORD
