Metadata-Version: 2.1
Name: finra-api-queries
Version: 1.2.1
Summary: An API wrapper for FINRA's Query API
Home-page: https://github.com/chencindyj/finra_api_queries
License: MIT
Author: Cindy Chen
Requires-Python: >=3.9,<4.0
Classifier: License :: OSI Approved :: MIT License
Classifier: Programming Language :: Python :: 3
Classifier: Programming Language :: Python :: 3.9
Classifier: Programming Language :: Python :: 3.10
Project-URL: Documentation, https://finra_api_queries.readthedocs.io
Project-URL: Repository, https://github.com/chencindyj/finra_api_queries
